efb_qq_plugin_mirai/ChatMgr.py
efb_qq_plugin_mirai/CustomTypes.py
efb_qq_plugin_mirai/MiraiConfig.py
efb_qq_plugin_mirai/MiraiFactory.py
efb_qq_plugin_mirai/MiraiMessageProcessor.py
efb_qq_plugin_mirai/MsgDecorator.py
efb_qq_plugin_mirai/Utils.py
efb_qq_plugin_mirai/__init__.py
efb_qq_plugin_mirai/__version__.py
efb_qq_plugin_mirai/mirai.py
efb_qq_plugin_mirai-2.0.9.dist-info/METADATA
efb_qq_plugin_mirai-2.0.9.dist-info/WHEEL
efb_qq_plugin_mirai-2.0.9.dist-info/entry_points.txt
efb_qq_plugin_mirai-2.0.9.dist-info/top_level.txt
efb_qq_plugin_mirai-2.0.9.dist-info/RECORD
