Metadata-Version: 2.1
Name: efb-qq-plugin-mirai
Version: 2.0.9
Summary: EQS plugin for mirai.
Home-page: https://github.com/milkice233/efb-qq-plugin-mirai
Author: Milkice
Author-email: milkice@milkice.me
License: GPLv3
Keywords: ehforwarderbot,EH Forwarder Bot,EH Forwarder Bot Slave Channel,qq,chatbot,EQS,mirai
Platform: UNKNOWN
Classifier: Development Status :: 3 - Alpha
Classifier: License :: OSI Approved :: GNU General Public License v3 (GPLv3)
Classifier: Intended Audience :: Developers
Classifier: Intended Audience :: End Users/Desktop
Classifier: Programming Language :: Python :: 3 :: Only
Classifier: Programming Language :: Python :: 3.6
Classifier: Programming Language :: Python :: 3.7
Classifier: Topic :: Communications :: Chat
Classifier: Topic :: Utilities
Requires-Python: >=3.6
Requires-Dist: efb-qq-slave
Requires-Dist: websocket-client
Requires-Dist: ehforwarderbot
Requires-Dist: python-magic
Requires-Dist: requests
Requires-Dist: python-mirai-core
Requires-Dist: cachetools
